LICENSE
README.md
setup.py
sculpting/__init__.py
sculpting/annotations.py
sculpting/core.py
sculpting/tools.py
sculpting.egg-info/PKG-INFO
sculpting.egg-info/SOURCES.txt
sculpting.egg-info/dependency_links.txt
sculpting.egg-info/requires.txt
sculpting.egg-info/top_level.txt