Metadata-Version: 2.1
Name: sculpting
Version: 1.0.0
Summary: Library for sculpting objects from others
Home-page: https://github.com/TheArtur128/Sculpting
Download-URL: https://github.com/TheArtur128/Sculpting/archive/refs/tags/v1.0.0.zip
Author: Arthur
Author-email: s9339307190@gmail.com
Keywords: library,tools,mapping,utils,data-mapping,annotations,mutability,object-mapping,attribute-mapping,method-mapping,imutability,utils-library
Classifier: Programming Language :: Python :: 3.11
Classifier: License :: OSI Approved :: GNU General Public License v3 (GPLv3)
Requires-Python: >=3.11
License-File: LICENSE
